LibFinFuncCharts/__init__.py
LibFinFuncCharts/ave_fixed_costs.py
LibFinFuncCharts/ave_total_costs.py
LibFinFuncCharts/ave_variable_costs.py
LibFinFuncCharts/bud_allocation_chart.py
LibFinFuncCharts/cal_ad_1_cur_assets_1.py
LibFinFuncCharts/cal_ad_1_cur_assets_2.py
LibFinFuncCharts/cal_inv_turn_days.py
LibFinFuncCharts/cal_inv_turn_times.py
LibFinFuncCharts/cal_own_work_cap_1.py
LibFinFuncCharts/cal_own_work_cap_2.py
LibFinFuncCharts/cal_turn_days.py
LibFinFuncCharts/cal_turn_times.py
LibFinFuncCharts/chart_inc_exp_year.py
LibFinFuncCharts/coef_el_dem.py
LibFinFuncCharts/comp_inter.py
LibFinFuncCharts/comp_inter_years.py
LibFinFuncCharts/demcurve.py
LibFinFuncCharts/el_of_dem.py
LibFinFuncCharts/employ_rate.py
LibFinFuncCharts/forecast_sales_year.py
LibFinFuncCharts/gross_nat_product_1.py
LibFinFuncCharts/gross_nat_product_2.py
LibFinFuncCharts/profit_cal.py
LibFinFuncCharts/real_income.py
LibFinFuncCharts/sel_revenue.py
LibFinFuncCharts/simple_inter.py
LibFinFuncCharts/supcurve.py
LibFinFuncCharts/unem_rate.py
LibFinFuncCharts/vol_defecit.py
LibFinFuncCharts/vol_surplus.py
libfinfunccharts-0.0.1.dist-info/METADATA
libfinfunccharts-0.0.1.dist-info/WHEEL
libfinfunccharts-0.0.1.dist-info/top_level.txt
libfinfunccharts-0.0.1.dist-info/RECORD
