Metadata-Version: 2.1
Name: libfinfunccharts
Version: 0.0.1
Summary: This library is a set of functions for financial calculations and the construction of charts and graphs.
Author: qu1cky
Author-email: qu1ck3r526@gmail.com
Project-URL: GitHub, https://github.com/qu1cky25/libfinfunc
Keywords: library finance charts
Classifier: Programming Language :: Python :: 3.11
Classifier: License :: OSI Approved :: MIT License
Classifier: Operating System :: OS Independent
Requires-Python: >=3.7
Requires-Dist: requests >=2.25.1
